fild_db/__init__.py
fild_db/client.py
fild_db/database.py
fild_db/types/__init__.py
fild_db/types/cassandra.py
fild_db/types/common.py
fild_db/types/model.py
fild_db/types/mysql.py
fild_db/types/postgres.py
fild_db-0.0.9.dist-info/licenses/LICENSE
fild_db-0.0.9.dist-info/METADATA
fild_db-0.0.9.dist-info/WHEEL
fild_db-0.0.9.dist-info/top_level.txt
fild_db-0.0.9.dist-info/RECORD
