Metadata-Version: 2.4
Name: fild-db
Version: 0.0.9
Summary: Operate with DB records using fild library
Home-page: https://github.com/elenakulgavaya/fild-db
Author: Elena Kulgavaya
Author-email: elena.kulgavaya@gmail.com
Project-URL: Bug Tracker, https://github.com/elenakulgavaya/fild-db/issues
Classifier: Programming Language :: Python :: 3
Classifier: License :: OSI Approved :: MIT License
Classifier: Operating System :: OS Independent
Requires-Python: >=3.9
License-File: LICENSE
Requires-Dist: fild>=0.1.0
Requires-Dist: fild-compare>=0.0.3
Dynamic: license-file
